removesalt/__init__.py
removesalt/build_guideline.py
removesalt/bundle.py
removesalt/main.py
removesalt/s3.py
removesalt/sign.py
removesalt/template.py
removesalt/apps/__init__.py
removesalt/apps/iris/__init__.py
removesalt/apps/iris/iris.py
removesalt/apps/mediaplayer/__init__.py
removesalt/apps/mediaplayer/mediaplayer.py
removesalt/apps/spectra/__init__.py
removesalt/apps/spectra/spectra.py
removesalt/conf/__init__.py
removesalt/conf/config.yaml
removesalt/conf/app/iris.yaml
removesalt/conf/app/mediaplayer.yaml
removesalt/conf/app/spectra.yaml
removesalt/conf/hydra/job_logging/custom.yaml
removesalt/templates/ClassicTheme.wxl
removesalt/templates/ClassicTheme.xml
removesalt/templates/iris/app.wxs
removesalt/templates/iris/bundle.wxs
removesalt/templates/iris/custom_actions.wxs
removesalt/templates/mediaplayer/app.wxs
removesalt/templates/mediaplayer/bundle.wxs
removesalt/templates/spectra/adobe.wxs
removesalt/templates/spectra/app.wxs
removesalt/templates/spectra/avid.wxs
removesalt/templates/spectra/bundle.wxs
removesalt/templates/spectra/custom_actions.wxs
removesalt/templates/spectra/ofx.wxs
removesalt/templates/spectra/spectraui.wxs
removesalt-0.6.0.dist-info/LICENSE.txt
removesalt-0.6.0.dist-info/METADATA
removesalt-0.6.0.dist-info/WHEEL
removesalt-0.6.0.dist-info/entry_points.txt
removesalt-0.6.0.dist-info/top_level.txt
removesalt-0.6.0.dist-info/RECORD
