Metadata-Version: 2.1
Name: removesalt
Version: 0.6.0
Summary: Add a short description here!
Home-page: https://github.com/pyscaffold/pyscaffold/
Author: Taylor Monacelli
Author-email: taylormonacelli@gmail.com
License: MPL-2.0
Project-URL: Documentation, https://pyscaffold.org/
Platform: any
Classifier: Development Status :: 4 - Beta
Classifier: Programming Language :: Python
License-File: LICENSE.txt
Requires-Dist: jinja2
Requires-Dist: giftmaster (>=0.0.52)
Requires-Dist: awscli
Requires-Dist: saltgang
Requires-Dist: hydra-core (>=1.2.0.dev1)
Requires-Dist: importlib-metadata ; python_version < "3.8"
Provides-Extra: testing
Requires-Dist: setuptools ; extra == 'testing'
Requires-Dist: pytest ; extra == 'testing'
Requires-Dist: pytest-cov ; extra == 'testing'
Requires-Dist: black ; extra == 'testing'
